model_mcp_sdk/ModelMcpSdk.py
model_mcp_sdk/__init__.py
model_mcp_sdk/core/HttpClient.py
model_mcp_sdk/core/ModelUrlConstant.py
model_mcp_sdk/core/SDKConfig.py
model_mcp_sdk/core/__init__.py
model_mcp_sdk/exceptions/SdkException.py
model_mcp_sdk/exceptions/__init__.py
model_mcp_sdk/model/ResponseVO.py
model_mcp_sdk/model/__init__.py
model_mcp_sdk/model/core/ReadNcRequest.py
model_mcp_sdk/model/core/__init__.py
model_mcp_sdk/model/nc/NcDimensions.py
model_mcp_sdk/model/nc/NcFileVO.py
model_mcp_sdk/model/nc/NcGlobalAttributes.py
model_mcp_sdk/model/nc/NcInfo.py
model_mcp_sdk/model/nc/NcVariables.py
model_mcp_sdk/model/nc/__init__.py
model_mcp_sdk/model/postprocess/BaseAchievements.py
model_mcp_sdk/model/postprocess/BaseGeoStr.py
model_mcp_sdk/model/postprocess/GetAchivementDetailRequestVO.py
model_mcp_sdk/model/postprocess/GetIndexRequestVO.py
model_mcp_sdk/model/postprocess/GetTimeLineWithPointRequestVO.py
model_mcp_sdk/model/postprocess/GetTimeLineWithPointResponseVO.py
model_mcp_sdk/model/postprocess/ShowSchemeModelElementVO.py
model_mcp_sdk/model/postprocess/ShowSchemeModelLetterItemVO.py
model_mcp_sdk/model/postprocess/__init__.py
model_mcp_sdk/model/service/ExeArgoServiceCallBackVO.py
model_mcp_sdk/model/service/ExeArgoServiceReqVO.py
model_mcp_sdk/model/service/ExeArgoServiceWorkflowResVO.py
model_mcp_sdk/model/service/KeyValueItem.py
model_mcp_sdk/model/service/WriteNcFileRspVO.py
model_mcp_sdk/model/service/__init__.py
model_mcp_sdk/service/ModelCoresService.py
model_mcp_sdk/service/PostprocessService.py
model_mcp_sdk/service/SchemeServiceService.py
model_mcp_sdk/service/SingleServiceService.py
model_mcp_sdk/service/SystemService.py
model_mcp_sdk/service/TokenService.py
model_mcp_sdk/service/__init__.py
model_mcp_sdk-1.0.2.dist-info/METADATA
model_mcp_sdk-1.0.2.dist-info/WHEEL
model_mcp_sdk-1.0.2.dist-info/top_level.txt
model_mcp_sdk-1.0.2.dist-info/RECORD
