Metadata-Version: 2.4
Name: model-mcp-sdk
Version: 1.0.2
Summary: sdk for yrihr mcp-platform
Home-page: https://www.yrihr.com.cn/
Author: gyf
Author-email: g75440081@qq.com
Classifier: Programming Language :: Python :: 3
Classifier: License :: OSI Approved :: MIT License
Requires-Dist: cachetools>=5.5.0
Requires-Dist: Requests>=2.32.4
Requires-Dist: urllib3>=2.5.0
